fuck_reborn/__init__.py
fuck_reborn/cli.py
fuck_reborn/core.py
fuck_reborn-0.1.4.dist-info/licenses/LICENSE
fuck_reborn-0.1.4.dist-info/METADATA
fuck_reborn-0.1.4.dist-info/WHEEL
fuck_reborn-0.1.4.dist-info/entry_points.txt
fuck_reborn-0.1.4.dist-info/top_level.txt
fuck_reborn-0.1.4.dist-info/RECORD
