Metadata-Version: 2.4
Name: fuck-reborn
Version: 0.1.4
Summary: AI-powered command corrector (like thefuck, but with Gemini)
Author-email: Surajit Sen <sensurajit@proton.me>
License: MIT
License-File: LICENSE
Requires-Dist: google-generativeai
Requires-Dist: python-dotenv
Dynamic: license-file
